LICENSE
MANIFEST.in
README.md
requirements.txt
setup.py
tests/__init__.py
tests/context.py
tests/test_coin.py
zvt_ccxt/__init__.py
zvt_ccxt/settings.py
zvt_ccxt.egg-info/PKG-INFO
zvt_ccxt.egg-info/SOURCES.txt
zvt_ccxt.egg-info/dependency_links.txt
zvt_ccxt.egg-info/entry_points.txt
zvt_ccxt.egg-info/requires.txt
zvt_ccxt.egg-info/top_level.txt
zvt_ccxt/accounts/__init__.py
zvt_ccxt/accounts/binance.json
zvt_ccxt/accounts/ccxt_account.py
zvt_ccxt/accounts/huobipro.json
zvt_ccxt/accounts/okex.json
zvt_ccxt/domain/__init__.py
zvt_ccxt/domain/coin_meta.py
zvt_ccxt/domain/quotes/__init__.py
zvt_ccxt/domain/quotes/gen_kdata_schema.py
zvt_ccxt/domain/quotes/coin/__init__.py
zvt_ccxt/domain/quotes/coin/coin_15m_kdata.py
zvt_ccxt/domain/quotes/coin/coin_1d_kdata.py
zvt_ccxt/domain/quotes/coin/coin_1h_kdata.py
zvt_ccxt/domain/quotes/coin/coin_1m_kdata.py
zvt_ccxt/domain/quotes/coin/coin_1mon_kdata.py
zvt_ccxt/domain/quotes/coin/coin_1wk_kdata.py
zvt_ccxt/domain/quotes/coin/coin_30m_kdata.py
zvt_ccxt/domain/quotes/coin/coin_4h_kdata.py
zvt_ccxt/domain/quotes/coin/coin_5m_kdata.py
zvt_ccxt/domain/quotes/coin/coin_tick_kdata.py
zvt_ccxt/recorders/__init__.py
zvt_ccxt/recorders/coin_kdata_recorder.py
zvt_ccxt/recorders/coin_recorder.py
zvt_ccxt/recorders/coin_tick_recorder.py