Metadata-Version: 2.1
Name: zvt-ccxt
Version: 0.0.6
Summary: ccxt cryptocurrency plugin for zvt 
Home-page: https://github.com/zvtvz/zvt-ccxt
Author: foolcage
Author-email: 5533061@qq.com
License: UNKNOWN
Project-URL: Bug Reports, https://github.com/zvtvz/zvt-ccxt/issues
Project-URL: Funding, https://github.com/zvtvz/zvt-ccxt
Project-URL: Say Thanks!, https://saythanks.io/to/foolcage
Project-URL: Source, https://github.com/zvtvz/zvt-ccxt
Keywords: quant zvt cryptocurrency coin btc eos
Platform: UNKNOWN
Classifier: Development Status :: 5 - Production/Stable
Classifier: Intended Audience :: Developers
Classifier: Intended Audience :: Customer Service
Classifier: Intended Audience :: Education
Classifier: Intended Audience :: Financial and Insurance Industry
Classifier: Topic :: Software Development :: Build Tools
Classifier: Topic :: Office/Business :: Financial :: Investment
Classifier: License :: OSI Approved :: MIT License
Classifier: Programming Language :: Python :: 3.6
Classifier: Programming Language :: Python :: 3.7
